ez_grid/__init__.py
ez_grid/utilities.py
ez_grid-0.1.3.dist-info/DESCRIPTION.rst
ez_grid-0.1.3.dist-info/METADATA
ez_grid-0.1.3.dist-info/RECORD
ez_grid-0.1.3.dist-info/WHEEL
ez_grid-0.1.3.dist-info/metadata.json
ez_grid-0.1.3.dist-info/top_level.txt
