Metadata-Version: 2.0
Name: ez-grid
Version: 0.1.3
Summary: A lightweight convenient grid class
